{
  "meta": {
    "category": "economy",
    "source_name": "BBC Business",
    "feed_url": "http://feeds.bbci.co.uk/news/business/rss.xml",
    "feed_title": "BBC News",
    "feed_link": "https://www.bbc.co.uk/news/business",
    "fetched_at_utc": "2026-04-04T14:40:08.080887+00:00",
    "entry_count": 56,
    "bozo": false,
    "failed": false,
    "failure_reason": ""
  },
  "items": [
    {
      "category": "economy",
      "source_name": "BBC Business",
      "feed_url": "http://feeds.bbci.co.uk/news/business/rss.xml",
      "title": "State pension age starts rising to 67 - here's how much you get and when",
      "link": "https://www.bbc.com/news/articles/cx2e7e90kneo?at_medium=RSS&at_campaign=rss",
      "summary": "The age at which people can start receiving the state pension is going up in stages over the next two years.",
      "published": "Fri, 03 Apr 2026 23:27:52 GMT",
      "updated": "Fri, 03 Apr 2026 23:27:52 GMT",
      "id": "https://www.bbc.com/news/articles/cx2e7e90kneo#0"
    },
    {
      "category": "economy",
      "source_name": "BBC Business",
      "feed_url": "http://feeds.bbci.co.uk/news/business/rss.xml",
      "title": "French-owned ship passes through Strait of Hormuz",
      "link": "https://www.bbc.com/news/articles/cjd8275jrrko?at_medium=RSS&at_campaign=rss",
      "summary": "It appears to be the first ship owned by a major European firm to go through the strait since the conflict began.",
      "published": "Fri, 03 Apr 2026 17:45:46 GMT",
      "updated": "Fri, 03 Apr 2026 17:45:46 GMT",
      "id": "https://www.bbc.com/news/articles/cjd8275jrrko#0"
    },
    {
      "category": "economy",
      "source_name": "BBC Business",
      "feed_url": "http://feeds.bbci.co.uk/news/business/rss.xml",
      "title": "'I ended up paying £500': Your subscription trap stories",
      "link": "https://www.bbc.com/news/articles/cz78lv9qej4o?at_medium=RSS&at_campaign=rss",
      "summary": "Many readers have experienced the ordeal of cancelling a subscription.",
      "published": "Thu, 02 Apr 2026 23:07:56 GMT",
      "updated": "Thu, 02 Apr 2026 23:07:56 GMT",
      "id": "https://www.bbc.com/news/articles/cz78lv9qej4o#0"
    },
    {
      "category": "economy",
      "source_name": "BBC Business",
      "feed_url": "http://feeds.bbci.co.uk/news/business/rss.xml",
      "title": "US jobs surge unexpectedly in March despite Iran war",
      "link": "https://www.bbc.com/news/articles/crk165g4vv3o?at_medium=RSS&at_campaign=rss",
      "summary": "Employers added 178,000 jobs, far more than had expected, the Labor Department says.",
      "published": "Fri, 03 Apr 2026 13:35:11 GMT",
      "updated": "Fri, 03 Apr 2026 13:35:11 GMT",
      "id": "https://www.bbc.com/news/articles/crk165g4vv3o#0"
    },
    {
      "category": "economy",
      "source_name": "BBC Business",
      "feed_url": "http://feeds.bbci.co.uk/news/business/rss.xml",
      "title": "M&S boss calls for more action on crime and abuse of staff",
      "link": "https://www.bbc.com/news/articles/crk16j2j1ygo?at_medium=RSS&at_campaign=rss",
      "summary": "Thinus Keeve's comments come days after an M&amp;S store was targeted during disorder in south London.",
      "published": "Fri, 03 Apr 2026 21:13:17 GMT",
      "updated": "Fri, 03 Apr 2026 21:13:17 GMT",
      "id": "https://www.bbc.com/news/articles/crk16j2j1ygo#0"
    },
    {
      "category": "economy",
      "source_name": "BBC Business",
      "feed_url": "http://feeds.bbci.co.uk/news/business/rss.xml",
      "title": "Oil prices jump and shares drop after Trump threatens more Iran strikes",
      "link": "https://www.bbc.com/news/articles/ce8lzd4v7zdo?at_medium=RSS&at_campaign=rss",
      "summary": "The US president said he'll bring Iran \"back to the Stone Age\" but gave no detail on ending the war.",
      "published": "Thu, 02 Apr 2026 22:25:44 GMT",
      "updated": "Thu, 02 Apr 2026 22:25:44 GMT",
      "id": "https://www.bbc.com/news/articles/ce8lzd4v7zdo#0"
    },
    {
      "category": "economy",
      "source_name": "BBC Business",
      "feed_url": "http://feeds.bbci.co.uk/news/business/rss.xml",
      "title": "New laws to make it easier to cancel subscriptions and get refunds",
      "link": "https://www.bbc.com/news/articles/cvg0v36ek2go?at_medium=RSS&at_campaign=rss",
      "summary": "Consumers will be able to cancel unwanted subscriptions 'at the click of a button', the government said.",
      "published": "Thu, 02 Apr 2026 09:08:40 GMT",
      "updated": "Thu, 02 Apr 2026 09:08:40 GMT",
      "id": "https://www.bbc.com/news/articles/cvg0v36ek2go#0"
    },
    {
      "category": "economy",
      "source_name": "BBC Business",
      "feed_url": "http://feeds.bbci.co.uk/news/business/rss.xml",
      "title": "A year on: Four ways Trump's tariffs have changed the global economy",
      "link": "https://www.bbc.com/news/articles/c79j1rd92ypo?at_medium=RSS&at_campaign=rss",
      "summary": "US tariffs stand at the highest rate in decades. But what has the impact been?",
      "published": "Thu, 02 Apr 2026 09:51:22 GMT",
      "updated": "Thu, 02 Apr 2026 09:51:22 GMT",
      "id": "https://www.bbc.com/news/articles/c79j1rd92ypo#1"
    },
    {
      "category": "economy",
      "source_name": "BBC Business",
      "feed_url": "http://feeds.bbci.co.uk/news/business/rss.xml",
      "title": "Pharmaceuticals face 100% tariffs in US - unless firms strike a deal",
      "link": "https://www.bbc.com/news/articles/cx29kke01gpo?at_medium=RSS&at_campaign=rss",
      "summary": "The order does not affect generic medicines, the most commonly used in the US.",
      "published": "Thu, 02 Apr 2026 22:06:30 GMT",
      "updated": "Thu, 02 Apr 2026 22:06:30 GMT",
      "id": "https://www.bbc.com/news/articles/cx29kke01gpo#1"
    },
    {
      "category": "economy",
      "source_name": "BBC Business",
      "feed_url": "http://feeds.bbci.co.uk/news/business/rss.xml",
      "title": "Petrol and diesel prices see biggest rise on record in March",
      "link": "https://www.bbc.com/news/articles/c20zgjzz0e4o?at_medium=RSS&at_campaign=rss",
      "summary": "The cost of filling a vehicle jumped at the sharpest pace than any other month, the RAC said.",
      "published": "Thu, 02 Apr 2026 07:41:37 GMT",
      "updated": "Thu, 02 Apr 2026 07:41:37 GMT",
      "id": "https://www.bbc.com/news/articles/c20zgjzz0e4o#1"
    },
    {
      "category": "economy",
      "source_name": "BBC Business",
      "feed_url": "http://feeds.bbci.co.uk/news/business/rss.xml",
      "title": "JLR sees sales recover after cyber attack",
      "link": "https://www.bbc.com/news/articles/c5yj9g89362o?at_medium=RSS&at_campaign=rss",
      "summary": "Work at plants in Solihull, Halewood and outside Wolverhampton restarted in October.",
      "published": "Thu, 02 Apr 2026 16:39:26 GMT",
      "updated": "Thu, 02 Apr 2026 16:39:26 GMT",
      "id": "https://www.bbc.com/news/articles/c5yj9g89362o#1"
    },
    {
      "category": "economy",
      "source_name": "BBC Business",
      "feed_url": "http://feeds.bbci.co.uk/news/business/rss.xml",
      "title": "Elon Musk's SpaceX set to be worth $1 trillion with planned public listing",
      "link": "https://www.bbc.com/news/articles/c2k35lg92dpo?at_medium=RSS&at_campaign=rss",
      "summary": "The company’s public stock debut is set to be one of the most valuable in history, and could make Musk the world's first trillionaire.",
      "published": "Thu, 02 Apr 2026 07:05:05 GMT",
      "updated": "Thu, 02 Apr 2026 07:05:05 GMT",
      "id": "https://www.bbc.com/news/articles/c2k35lg92dpo#1"
    },
    {
      "category": "economy",
      "source_name": "BBC Business",
      "feed_url": "http://feeds.bbci.co.uk/news/business/rss.xml",
      "title": "Estate agents accuse Rightmove of charging excessive fees",
      "link": "https://www.bbc.com/news/articles/cn0yle5rrp8o?at_medium=RSS&at_campaign=rss",
      "summary": "The online listing portal is now being pursued in a class action, launched on behalf of potentially hundreds of estate agents.",
      "published": "Wed, 01 Apr 2026 08:15:36 GMT",
      "updated": "Wed, 01 Apr 2026 08:15:36 GMT",
      "id": "https://www.bbc.com/news/articles/cn0yle5rrp8o#1"
    },
    {
      "category": "economy",
      "source_name": "BBC Business",
      "feed_url": "http://feeds.bbci.co.uk/news/business/rss.xml",
      "title": "Warning Iran war 'shock' could push up mortgages for 1.3m homeowners",
      "link": "https://www.bbc.com/news/articles/c895pqepwv2o?at_medium=RSS&at_campaign=rss",
      "summary": "Higher energy prices could lead to higher borrowing costs for homeowners, the Bank warns.",
      "published": "Wed, 01 Apr 2026 10:47:02 GMT",
      "updated": "Wed, 01 Apr 2026 10:47:02 GMT",
      "id": "https://www.bbc.com/news/articles/c895pqepwv2o#1"
    },
    {
      "category": "economy",
      "source_name": "BBC Business",
      "feed_url": "http://feeds.bbci.co.uk/news/business/rss.xml",
      "title": "Energy bill help would be based on household income, Reeves says",
      "link": "https://www.bbc.com/news/articles/cgk0d76yg8po?at_medium=RSS&at_campaign=rss",
      "summary": "The chancellor tells the BBC it is \"too early\" to say exactly who would get help but hinted any support would not arrive until the autumn.",
      "published": "Wed, 01 Apr 2026 08:07:51 GMT",
      "updated": "Wed, 01 Apr 2026 08:07:51 GMT",
      "id": "https://www.bbc.com/news/articles/cgk0d76yg8po#1"
    },
    {
      "category": "economy",
      "source_name": "BBC Business",
      "feed_url": "http://feeds.bbci.co.uk/news/business/rss.xml",
      "title": "Minimum wage rises to £12.71 an hour as firms warn of impact",
      "link": "https://www.bbc.com/news/articles/c36r7jk6093o?at_medium=RSS&at_campaign=rss",
      "summary": "Many businesses have said they will have to pass higher wage costs onto customers.",
      "published": "Wed, 01 Apr 2026 13:45:44 GMT",
      "updated": "Wed, 01 Apr 2026 13:45:44 GMT",
      "id": "https://www.bbc.com/news/articles/c36r7jk6093o#1"
    },
    {
      "category": "economy",
      "source_name": "BBC Business",
      "feed_url": "http://feeds.bbci.co.uk/news/business/rss.xml",
      "title": "From water to council tax: How the bill rises (and one drop) affect you",
      "link": "https://www.bbc.com/news/articles/clyeke8z871o?at_medium=RSS&at_campaign=rss",
      "summary": "A string of bill increases have taken effect but minimum wage and benefit rises will help some to pay them.",
      "published": "Tue, 31 Mar 2026 23:00:54 GMT",
      "updated": "Tue, 31 Mar 2026 23:00:54 GMT",
      "id": "https://www.bbc.com/news/articles/clyeke8z871o#1"
    },
    {
      "category": "economy",
      "source_name": "BBC Business",
      "feed_url": "http://feeds.bbci.co.uk/news/business/rss.xml",
      "title": "Topps Tiles to close 23 stores over rising costs",
      "link": "https://www.bbc.com/news/articles/c1d9ezye37zo?at_medium=RSS&at_campaign=rss",
      "summary": "Topps Tiles says eight stores have already closed - with the rest to shut over the next six months.",
      "published": "Wed, 01 Apr 2026 08:58:50 GMT",
      "updated": "Wed, 01 Apr 2026 08:58:50 GMT",
      "id": "https://www.bbc.com/news/articles/c1d9ezye37zo#1"
    },
    {
      "category": "economy",
      "source_name": "BBC Business",
      "feed_url": "http://feeds.bbci.co.uk/news/business/rss.xml",
      "title": "IndiGo names former British Airways chief Willie Walsh as CEO",
      "link": "https://www.bbc.com/news/articles/cz6739j210qo?at_medium=RSS&at_campaign=rss",
      "summary": "The announcement comes days after former CEO Pieter Elbers quit in the backdrop of a flight cancellation crisis.",
      "published": "Wed, 01 Apr 2026 06:33:08 GMT",
      "updated": "Wed, 01 Apr 2026 06:33:08 GMT",
      "id": "https://www.bbc.com/news/articles/cz6739j210qo#1"
    },
    {
      "category": "economy",
      "source_name": "BBC Business",
      "feed_url": "http://feeds.bbci.co.uk/news/business/rss.xml",
      "title": "Thousands lose their jobs in deep cuts at tech giant Oracle",
      "link": "https://www.bbc.com/news/articles/cm296jzzl9yo?at_medium=RSS&at_campaign=rss",
      "summary": "It is thought that thousands of people may have lost their jobs at Oracle, one of the world's largest tech companies.",
      "published": "Wed, 01 Apr 2026 07:09:46 GMT",
      "updated": "Wed, 01 Apr 2026 07:09:46 GMT",
      "id": "https://www.bbc.com/news/articles/cm296jzzl9yo#1"
    },
    {
      "category": "economy",
      "source_name": "BBC Business",
      "feed_url": "http://feeds.bbci.co.uk/news/business/rss.xml",
      "title": "Oil briefly falls below $100 and shares jump on Trump Iran war pledge",
      "link": "https://www.bbc.com/news/articles/c2489v97842o?at_medium=RSS&at_campaign=rss",
      "summary": "European stock markets opened higher after the US president said the conflict would \"end very soon\".",
      "published": "Wed, 01 Apr 2026 08:49:19 GMT",
      "updated": "Wed, 01 Apr 2026 08:49:19 GMT",
      "id": "https://www.bbc.com/news/articles/c2489v97842o#1"
    },
    {
      "category": "economy",
      "source_name": "BBC Business",
      "feed_url": "http://feeds.bbci.co.uk/news/business/rss.xml",
      "title": "Asia's migrant workers debate if Gulf jobs are worth deadly risk of Iran war",
      "link": "https://www.bbc.com/news/articles/c0kr8lrpekmo?at_medium=RSS&at_campaign=rss",
      "summary": "Iran's strikes on Gulf states have been especially hard for migrants who have long supported these economies to lift their families back home from poverty.",
      "published": "Tue, 31 Mar 2026 22:48:34 GMT",
      "updated": "Tue, 31 Mar 2026 22:48:34 GMT",
      "id": "https://www.bbc.com/news/articles/c0kr8lrpekmo#1"
    },
    {
      "category": "economy",
      "source_name": "BBC Business",
      "feed_url": "http://feeds.bbci.co.uk/news/business/rss.xml",
      "title": "Oil nears highest price since start of Iran war",
      "link": "https://www.bbc.com/news/articles/c17vrd0pj95o?at_medium=RSS&at_campaign=rss",
      "summary": "The US-Israel Iran war has halted almost all traffic in a key waterway and the price Brent crude has surged.",
      "published": "Tue, 31 Mar 2026 22:34:04 GMT",
      "updated": "Tue, 31 Mar 2026 22:34:04 GMT",
      "id": "https://www.bbc.com/news/articles/c17vrd0pj95o#1"
    },
    {
      "category": "economy",
      "source_name": "BBC Business",
      "feed_url": "http://feeds.bbci.co.uk/news/business/rss.xml",
      "title": "'I sent eight letters': Drivers hope for payout from car finance redress scheme",
      "link": "https://www.bbc.com/news/articles/c20dxdy33llo?at_medium=RSS&at_campaign=rss",
      "summary": "Millions of motorists could be entitled to compensation with the financial regulator setting out how to apply",
      "published": "Tue, 31 Mar 2026 10:14:03 GMT",
      "updated": "Tue, 31 Mar 2026 10:14:03 GMT",
      "id": "https://www.bbc.com/news/articles/c20dxdy33llo#1"
    },
    {
      "category": "economy",
      "source_name": "BBC Business",
      "feed_url": "http://feeds.bbci.co.uk/news/business/rss.xml",
      "title": "Housing market to soften amid Iran war fallout, Nationwide says",
      "link": "https://www.bbc.com/news/articles/ckgwe7k49d7o?at_medium=RSS&at_campaign=rss",
      "summary": "The lender says the market regained momentum in March, but rising mortgage and energy costs could hit consumer confidence.",
      "published": "Tue, 31 Mar 2026 09:47:33 GMT",
      "updated": "Tue, 31 Mar 2026 09:47:33 GMT",
      "id": "https://www.bbc.com/news/articles/ckgwe7k49d7o#1"
    },
    {
      "category": "economy",
      "source_name": "BBC Business",
      "feed_url": "http://feeds.bbci.co.uk/news/business/rss.xml",
      "title": "US petrol price tops $4 for first time since 2022",
      "link": "https://www.bbc.com/news/articles/cn8d47vzz13o?at_medium=RSS&at_campaign=rss",
      "summary": "The Iran war continues to push up prices at the pump for US motorists.",
      "published": "Tue, 31 Mar 2026 17:17:53 GMT",
      "updated": "Tue, 31 Mar 2026 17:17:53 GMT",
      "id": "https://www.bbc.com/news/articles/cn8d47vzz13o#1"
    },
    {
      "category": "economy",
      "source_name": "BBC Business",
      "feed_url": "http://feeds.bbci.co.uk/news/business/rss.xml",
      "title": "Are domes and spheres the future of entertainment?",
      "link": "https://www.bbc.com/news/articles/cq6q66n86qyo?at_medium=RSS&at_campaign=rss",
      "summary": "Rivals are emerging for the Las Vegas Sphere - are domes and spheres the future for entertainment?",
      "published": "Mon, 30 Mar 2026 23:29:15 GMT",
      "updated": "Mon, 30 Mar 2026 23:29:15 GMT",
      "id": "https://www.bbc.com/news/articles/cq6q66n86qyo#2"
    },
    {
      "category": "economy",
      "source_name": "BBC Business",
      "feed_url": "http://feeds.bbci.co.uk/news/business/rss.xml",
      "title": "Why Chinese tech companies are racing to set up in Hong Kong",
      "link": "https://www.bbc.com/news/articles/c8d5v404m96o?at_medium=RSS&at_campaign=rss",
      "summary": "Mainland firms are using the territory to test products and as a springboard for global expansion.",
      "published": "Sun, 29 Mar 2026 23:07:12 GMT",
      "updated": "Sun, 29 Mar 2026 23:07:12 GMT",
      "id": "https://www.bbc.com/news/articles/c8d5v404m96o#2"
    },
    {
      "category": "economy",
      "source_name": "BBC Business",
      "feed_url": "http://feeds.bbci.co.uk/news/business/rss.xml",
      "title": "How will car finance compensation payments work?",
      "link": "https://www.bbc.com/news/articles/c2l9vvj097lo?at_medium=RSS&at_campaign=rss",
      "summary": "Millions could be entitled to compensation as a result of commission arrangements between lenders and dealers.",
      "published": "Tue, 31 Mar 2026 09:47:58 GMT",
      "updated": "Tue, 31 Mar 2026 09:47:58 GMT",
      "id": "https://www.bbc.com/news/articles/c2l9vvj097lo#2"
    },
    {
      "category": "economy",
      "source_name": "BBC Business",
      "feed_url": "http://feeds.bbci.co.uk/news/business/rss.xml",
      "title": "The spiky cactus fruit giving Indian farmers a cash boost",
      "link": "https://www.bbc.com/news/articles/c3ewyyjjzkwo?at_medium=RSS&at_campaign=rss",
      "summary": "Indian farmers are turning to dragon fruit as a profitable alternative to mangoes and coffee.",
      "published": "Fri, 27 Mar 2026 00:01:01 GMT",
      "updated": "Fri, 27 Mar 2026 00:01:01 GMT",
      "id": "https://www.bbc.com/news/articles/c3ewyyjjzkwo#2"
    },
    {
      "category": "economy",
      "source_name": "BBC Business",
      "feed_url": "http://feeds.bbci.co.uk/news/business/rss.xml",
      "title": "The homeless teenager who became a successful advertising boss",
      "link": "https://www.bbc.com/news/articles/cn08lx745ndo?at_medium=RSS&at_campaign=rss",
      "summary": "Greg Daily has swapped sleeping on friends' sofas for running a popular digital marketing company.",
      "published": "Thu, 26 Mar 2026 00:03:36 GMT",
      "updated": "Thu, 26 Mar 2026 00:03:36 GMT",
      "id": "https://www.bbc.com/news/articles/cn08lx745ndo#2"
    },
    {
      "category": "economy",
      "source_name": "BBC Business",
      "feed_url": "http://feeds.bbci.co.uk/news/business/rss.xml",
      "title": "Would you build your own apps?",
      "link": "https://www.bbc.com/news/articles/cwy8wxgmgd1o?at_medium=RSS&at_campaign=rss",
      "summary": "Start-ups are offering tech for novices to create apps with the help of AI.",
      "published": "Tue, 24 Mar 2026 00:36:02 GMT",
      "updated": "Tue, 24 Mar 2026 00:36:02 GMT",
      "id": "https://www.bbc.com/news/articles/cwy8wxgmgd1o#2"
    },
    {
      "category": "economy",
      "source_name": "BBC Business",
      "feed_url": "http://feeds.bbci.co.uk/news/business/rss.xml",
      "title": "US weight-loss drugmakers slash prices in fight to win customers",
      "link": "https://www.bbc.com/news/articles/c5yg6kyd9dzo?at_medium=RSS&at_campaign=rss",
      "summary": "Weight-loss drug prices are falling in the US - but can the example be repeated?",
      "published": "Mon, 23 Mar 2026 06:03:48 GMT",
      "updated": "Mon, 23 Mar 2026 06:03:48 GMT",
      "id": "https://www.bbc.com/news/articles/c5yg6kyd9dzo#2"
    },
    {
      "category": "economy",
      "source_name": "BBC Business",
      "feed_url": "http://feeds.bbci.co.uk/news/business/rss.xml",
      "title": "Germany has a shortage of workers - so it's turning to India for help",
      "link": "https://www.bbc.com/news/articles/c3wlww83yv4o?at_medium=RSS&at_campaign=rss",
      "summary": "The European nation, struggling to find skilled staff, is giving jobs to young people from India.",
      "published": "Mon, 23 Mar 2026 00:03:25 GMT",
      "updated": "Mon, 23 Mar 2026 00:03:25 GMT",
      "id": "https://www.bbc.com/news/articles/c3wlww83yv4o#2"
    },
    {
      "category": "economy",
      "source_name": "BBC Business",
      "feed_url": "http://feeds.bbci.co.uk/news/business/rss.xml",
      "title": "'Club vibes without the hangover': The twenty-somethings going out - in the gym",
      "link": "https://www.bbc.com/news/articles/cly0krjy57lo?at_medium=RSS&at_campaign=rss",
      "summary": "Young people are driving a gym boom as more fitness spaces are transformed into vibrant hangouts.",
      "published": "Sun, 22 Mar 2026 00:56:15 GMT",
      "updated": "Sun, 22 Mar 2026 00:56:15 GMT",
      "id": "https://www.bbc.com/news/articles/cly0krjy57lo#2"
    },
    {
      "category": "economy",
      "source_name": "BBC Business",
      "feed_url": "http://feeds.bbci.co.uk/news/business/rss.xml",
      "title": "Home working, long leases and rise of parking apps - what went wrong for NCP",
      "link": "https://www.bbc.com/news/articles/cgl5rwgr5l2o?at_medium=RSS&at_campaign=rss",
      "summary": "How could a company that charged as much as £65 for a day's parking fail to turn a profit?",
      "published": "Sat, 21 Mar 2026 01:59:52 GMT",
      "updated": "Sat, 21 Mar 2026 01:59:52 GMT",
      "id": "https://www.bbc.com/news/articles/cgl5rwgr5l2o#2"
    },
    {
      "category": "economy",
      "source_name": "BBC Business",
      "feed_url": "http://feeds.bbci.co.uk/news/business/rss.xml",
      "title": "Colombia's budding tech scene needs a cash boost",
      "link": "https://www.bbc.com/news/articles/c4g2kyg4e78o?at_medium=RSS&at_campaign=rss",
      "summary": "Colombia has become a tech hub for Latin America, but attracting investors is a challenge.",
      "published": "Fri, 20 Mar 2026 00:09:01 GMT",
      "updated": "Fri, 20 Mar 2026 00:09:01 GMT",
      "id": "https://www.bbc.com/news/articles/c4g2kyg4e78o#2"
    },
    {
      "category": "economy",
      "source_name": "BBC Business",
      "feed_url": "http://feeds.bbci.co.uk/news/business/rss.xml",
      "title": "How Finnish supermarkets are central to the country's defence",
      "link": "https://www.bbc.com/news/articles/cly1mg3zy20o?at_medium=RSS&at_campaign=rss",
      "summary": "The chains all have detailed plans to follow in the event of the nation going to war.",
      "published": "Thu, 19 Mar 2026 00:10:45 GMT",
      "updated": "Thu, 19 Mar 2026 00:10:45 GMT",
      "id": "https://www.bbc.com/news/articles/cly1mg3zy20o#2"
    },
    {
      "category": "economy",
      "source_name": "BBC Business",
      "feed_url": "http://feeds.bbci.co.uk/news/business/rss.xml",
      "title": "Is it possible to build a plastic-free home?",
      "link": "https://www.bbc.com/news/articles/cy4wemk4dzvo?at_medium=RSS&at_campaign=rss",
      "summary": "Using plastic in construction is cheap and easy, but some are trying to radically cut back its use.",
      "published": "Tue, 17 Mar 2026 00:01:31 GMT",
      "updated": "Tue, 17 Mar 2026 00:01:31 GMT",
      "id": "https://www.bbc.com/news/articles/cy4wemk4dzvo#2"
    },
    {
      "category": "economy",
      "source_name": "BBC Business",
      "feed_url": "http://feeds.bbci.co.uk/news/business/rss.xml",
      "title": "Ukraine's urgent fight on the financial frontline",
      "link": "https://www.bbc.com/news/articles/c20jyngz7ygo?at_medium=RSS&at_campaign=rss",
      "summary": "The war-torn country is battling to secure crucial funding from the IMF and EU, as well as putting up taxes.",
      "published": "Mon, 16 Mar 2026 00:06:14 GMT",
      "updated": "Mon, 16 Mar 2026 00:06:14 GMT",
      "id": "https://www.bbc.com/news/articles/c20jyngz7ygo#2"
    },
    {
      "category": "economy",
      "source_name": "BBC Business",
      "feed_url": "http://feeds.bbci.co.uk/news/business/rss.xml",
      "title": "Can plastic-eating fungi help clean up nappy waste?",
      "link": "https://www.bbc.com/news/articles/cvg3wg0yrp5o?at_medium=RSS&at_campaign=rss",
      "summary": "Cost and convenience have made disposable nappies dominant - can start-ups compete?",
      "published": "Fri, 13 Mar 2026 00:03:14 GMT",
      "updated": "Fri, 13 Mar 2026 00:03:14 GMT",
      "id": "https://www.bbc.com/news/articles/cvg3wg0yrp5o#2"
    },
    {
      "category": "economy",
      "source_name": "BBC Business",
      "feed_url": "http://feeds.bbci.co.uk/news/business/rss.xml",
      "title": "Why has Trump eased sanctions on Russian oil - and will it help Putin?",
      "link": "https://www.bbc.com/news/articles/cm2871wyz9ko?at_medium=RSS&at_campaign=rss",
      "summary": "The US said easing sanctions on Russian oil would provide only a limited financial boost to Putin.",
      "published": "Fri, 13 Mar 2026 16:07:39 GMT",
      "updated": "Fri, 13 Mar 2026 16:07:39 GMT",
      "id": "https://www.bbc.com/news/articles/cm2871wyz9ko#2"
    },
    {
      "category": "economy",
      "source_name": "BBC Business",
      "feed_url": "http://feeds.bbci.co.uk/news/business/rss.xml",
      "title": "State pension age starts rising to 67 - here's how much you get and when",
      "link": "https://www.bbc.com/news/articles/cx2e7e90kneo?at_medium=RSS&at_campaign=rss",
      "summary": "The age at which people can start receiving the state pension is going up in stages over the next two years.",
      "published": "Fri, 03 Apr 2026 23:27:52 GMT",
      "updated": "Fri, 03 Apr 2026 23:27:52 GMT",
      "id": "https://www.bbc.com/news/articles/cx2e7e90kneo#4"
    },
    {
      "category": "economy",
      "source_name": "BBC Business",
      "feed_url": "http://feeds.bbci.co.uk/news/business/rss.xml",
      "title": "No jet fuel shortage for '4 to 6 weeks' - airline",
      "link": "https://www.bbc.com/news/articles/c208ryxy23ko?at_medium=RSS&at_campaign=rss",
      "summary": "No shortage but Aurigny is spending 120% more on fuel than it was prior to the war, its boss says.",
      "published": "Fri, 03 Apr 2026 14:59:29 GMT",
      "updated": "Fri, 03 Apr 2026 14:59:29 GMT",
      "id": "https://www.bbc.com/news/articles/c208ryxy23ko#4"
    },
    {
      "category": "economy",
      "source_name": "BBC Business",
      "feed_url": "http://feeds.bbci.co.uk/news/business/rss.xml",
      "title": "National Minimum Wage rises this week",
      "link": "https://www.bbc.com/news/videos/cdxd5kkpz7xo?at_medium=RSS&at_campaign=rss",
      "summary": "Around 2.7 million people are set to receive a pay rise this week as the national minimum wage goes up by 50p to £12.71 for over 21s.",
      "published": "Thu, 02 Apr 2026 16:11:00 GMT",
      "updated": "Thu, 02 Apr 2026 16:11:00 GMT",
      "id": "https://www.bbc.com/news/videos/cdxd5kkpz7xo#4"
    },
    {
      "category": "economy",
      "source_name": "BBC Business",
      "feed_url": "http://feeds.bbci.co.uk/news/business/rss.xml",
      "title": "New laws to make it easier to cancel subscriptions",
      "link": "https://www.bbc.com/news/videos/cdxklq3kqlro?at_medium=RSS&at_campaign=rss",
      "summary": "A crackdown on \"subscription traps\" could save the average person nearly £170 a year, according to the Department for Business and Trade.",
      "published": "Thu, 02 Apr 2026 15:15:33 GMT",
      "updated": "Thu, 02 Apr 2026 15:15:33 GMT",
      "id": "https://www.bbc.com/news/videos/cdxklq3kqlro#4"
    },
    {
      "category": "economy",
      "source_name": "BBC Business",
      "feed_url": "http://feeds.bbci.co.uk/news/business/rss.xml",
      "title": "What is the triple lock and how much is the state pension worth?",
      "link": "https://www.bbc.com/news/articles/cq6m03ld7nvo?at_medium=RSS&at_campaign=rss",
      "summary": "The triple lock guarantees that the state pension is not overtaken by inflation or wage increases.",
      "published": "Thu, 02 Apr 2026 14:47:27 GMT",
      "updated": "Thu, 02 Apr 2026 14:47:27 GMT",
      "id": "https://www.bbc.com/news/articles/cq6m03ld7nvo#4"
    },
    {
      "category": "economy",
      "source_name": "BBC Business",
      "feed_url": "http://feeds.bbci.co.uk/news/business/rss.xml",
      "title": "The £5.30 orange juice that tells the story of why supermarket prices are sky high",
      "link": "https://www.bbc.com/news/articles/c397n3jl3z8o?at_medium=RSS&at_campaign=rss",
      "summary": "Butter, chocolate, coffee and milk have all seen prices rocket. Tracing back through the story of one particular supermarket staple begins to explain why",
      "published": "Sat, 28 Mar 2026 06:30:45 GMT",
      "updated": "Sat, 28 Mar 2026 06:30:45 GMT",
      "id": "https://www.bbc.com/news/articles/c397n3jl3z8o#5"
    },
    {
      "category": "economy",
      "source_name": "BBC Business",
      "feed_url": "http://feeds.bbci.co.uk/news/business/rss.xml",
      "title": "Prepare for turbulence - how a prolonged Middle East conflict could reshape how we fly",
      "link": "https://www.bbc.com/news/articles/cn08x9lw0pzo?at_medium=RSS&at_campaign=rss",
      "summary": "The Gulf's hub airports made long-distance travel cheaper - but now their future looks unclear.",
      "published": "Thu, 26 Mar 2026 00:41:16 GMT",
      "updated": "Thu, 26 Mar 2026 00:41:16 GMT",
      "id": "https://www.bbc.com/news/articles/cn08x9lw0pzo#5"
    },
    {
      "category": "economy",
      "source_name": "BBC Business",
      "feed_url": "http://feeds.bbci.co.uk/news/business/rss.xml",
      "title": "Sir John Curtice: Why Labour's Brexit focus has shifted from Leavers to Remainers",
      "link": "https://www.bbc.com/news/articles/c4gjn1d74jlo?at_medium=RSS&at_campaign=rss",
      "summary": "Will the pursuit of a closer relationship with the EU risk courting electoral disaster by alienating Brexit-backing voters?",
      "published": "Fri, 20 Mar 2026 00:01:51 GMT",
      "updated": "Fri, 20 Mar 2026 00:01:51 GMT",
      "id": "https://www.bbc.com/news/articles/c4gjn1d74jlo#5"
    },
    {
      "category": "economy",
      "source_name": "BBC Business",
      "feed_url": "http://feeds.bbci.co.uk/news/business/rss.xml",
      "title": "The real impact of roadworks on the country - and why they're set to get worse",
      "link": "https://www.bbc.com/news/articles/c23e3d1r17go?at_medium=RSS&at_campaign=rss",
      "summary": "There is a fine balance between the benefits of improved infrastructure, versus the cost of disruption. Does the country have it right?",
      "published": "Sun, 11 Jan 2026 01:26:18 GMT",
      "updated": "Sun, 11 Jan 2026 01:26:18 GMT",
      "id": "https://www.bbc.com/news/articles/c23e3d1r17go#5"
    },
    {
      "category": "economy",
      "source_name": "BBC Business",
      "feed_url": "http://feeds.bbci.co.uk/news/business/rss.xml",
      "title": "Why the railways often seem to be in such chaos over Christmas",
      "link": "https://www.bbc.com/news/articles/czdg795m5epo?at_medium=RSS&at_campaign=rss",
      "summary": "Parts of Britain’s rail network will close for engineering work over the festive period - but is that the right time to do it?",
      "published": "Mon, 22 Dec 2025 00:03:12 GMT",
      "updated": "Mon, 22 Dec 2025 00:03:12 GMT",
      "id": "https://www.bbc.com/news/articles/czdg795m5epo#5"
    },
    {
      "category": "economy",
      "source_name": "BBC Business",
      "feed_url": "http://feeds.bbci.co.uk/news/business/rss.xml",
      "title": "National Minimum Wage rises this week",
      "link": "https://www.bbc.com/news/videos/cdxd5kkpz7xo?at_medium=RSS&at_campaign=rss",
      "summary": "Around 2.7 million people are set to receive a pay rise this week as the national minimum wage goes up by 50p to £12.71 for over 21s.",
      "published": "Thu, 02 Apr 2026 16:11:00 GMT",
      "updated": "Thu, 02 Apr 2026 16:11:00 GMT",
      "id": "https://www.bbc.com/news/videos/cdxd5kkpz7xo#6"
    },
    {
      "category": "economy",
      "source_name": "BBC Business",
      "feed_url": "http://feeds.bbci.co.uk/news/business/rss.xml",
      "title": "New laws to make it easier to cancel subscriptions",
      "link": "https://www.bbc.com/news/videos/cdxklq3kqlro?at_medium=RSS&at_campaign=rss",
      "summary": "A crackdown on \"subscription traps\" could save the average person nearly £170 a year, according to the Department for Business and Trade.",
      "published": "Thu, 02 Apr 2026 15:15:33 GMT",
      "updated": "Thu, 02 Apr 2026 15:15:33 GMT",
      "id": "https://www.bbc.com/news/videos/cdxklq3kqlro#6"
    },
    {
      "category": "economy",
      "source_name": "BBC Business",
      "feed_url": "http://feeds.bbci.co.uk/news/business/rss.xml",
      "title": "'Affordability is the biggest thing' - Conservatives mixed on economy under Trump",
      "link": "https://www.bbc.com/news/videos/cn08y2jgdxpo?at_medium=RSS&at_campaign=rss",
      "summary": "Conservatives gathered at the annual CPAC conference in Texas were mixed when asked about their feelings on the current economy.",
      "published": "Fri, 27 Mar 2026 00:01:51 GMT",
      "updated": "Fri, 27 Mar 2026 00:01:51 GMT",
      "id": "https://www.bbc.com/news/videos/cn08y2jgdxpo#6"
    },
    {
      "category": "economy",
      "source_name": "BBC Business",
      "feed_url": "http://feeds.bbci.co.uk/news/business/rss.xml",
      "title": "Who knew Lord Sugar is a table tennis fan?",
      "link": "https://www.bbc.com/news/videos/crr109r2gd4o?at_medium=RSS&at_campaign=rss",
      "summary": "The Apprentice candidates try to sell a table tennis set live on TV.",
      "published": "Thu, 26 Mar 2026 22:42:12 GMT",
      "updated": "Thu, 26 Mar 2026 22:42:12 GMT",
      "id": "https://www.bbc.com/news/videos/crr109r2gd4o#6"
    }
  ]
}