{
  "meta": {
    "category": "politics",
    "source_name": "BBC World",
    "feed_url": "http://feeds.bbci.co.uk/news/world/rss.xml",
    "feed_title": "BBC News",
    "feed_link": "https://www.bbc.co.uk/news/world",
    "fetched_at_utc": "2026-04-07T08:52:01.953780+00:00",
    "entry_count": 25,
    "bozo": false,
    "failed": false,
    "failure_reason": ""
  },
  "items": [
    {
      "category": "politics",
      "source_name": "BBC World",
      "feed_url": "http://feeds.bbci.co.uk/news/world/rss.xml",
      "title": "Little sign of breakthrough as Trump's Iran deadline nears",
      "link": "https://www.bbc.com/news/articles/czexw94rj5jo?at_medium=RSS&at_campaign=rss",
      "summary": "The US president is in a delicate political position as the final hours to Tuesday's deadline for Iran to open the Strait of Hormuz tick down.",
      "published": "Mon, 06 Apr 2026 23:04:23 GMT",
      "updated": "Mon, 06 Apr 2026 23:04:23 GMT",
      "id": "https://www.bbc.com/news/articles/czexw94rj5jo#0"
    },
    {
      "category": "politics",
      "source_name": "BBC World",
      "feed_url": "http://feeds.bbci.co.uk/news/world/rss.xml",
      "title": "Australia's most-decorated living soldier charged over alleged war crimes",
      "link": "https://www.bbc.com/news/articles/crr1jyk0qwjo?at_medium=RSS&at_campaign=rss",
      "summary": "Ben Roberts-Smith, who denies all wrongdoing, previously lost a landmark defamation case over the alleged murders.",
      "published": "Tue, 07 Apr 2026 07:19:27 GMT",
      "updated": "Tue, 07 Apr 2026 07:19:27 GMT",
      "id": "https://www.bbc.com/news/articles/crr1jyk0qwjo#0"
    },
    {
      "category": "politics",
      "source_name": "BBC World",
      "feed_url": "http://feeds.bbci.co.uk/news/world/rss.xml",
      "title": "JD Vance due in Hungary to back Orban's re-election bid",
      "link": "https://www.bbc.com/news/articles/cyv16lq2rp1o?at_medium=RSS&at_campaign=rss",
      "summary": "The US vice-president's visit is the latest show of White House support for the Hungarian leader.",
      "published": "Tue, 07 Apr 2026 01:45:41 GMT",
      "updated": "Tue, 07 Apr 2026 01:45:41 GMT",
      "id": "https://www.bbc.com/news/articles/cyv16lq2rp1o#0"
    },
    {
      "category": "politics",
      "source_name": "BBC World",
      "feed_url": "http://feeds.bbci.co.uk/news/world/rss.xml",
      "title": "Taiwan opposition leader visits China for expected meeting with Xi Jinping",
      "link": "https://www.bbc.com/news/articles/c0krnz7mmmjo?at_medium=RSS&at_campaign=rss",
      "summary": "Cheng Li-wun said she \"gladly accepted\" Xi Jinping's invitation and hopes to be a \"bridge for peace\".",
      "published": "Tue, 07 Apr 2026 07:29:55 GMT",
      "updated": "Tue, 07 Apr 2026 07:29:55 GMT",
      "id": "https://www.bbc.com/news/articles/c0krnz7mmmjo#0"
    },
    {
      "category": "politics",
      "source_name": "BBC World",
      "feed_url": "http://feeds.bbci.co.uk/news/world/rss.xml",
      "title": "Nine policemen sentenced to death in India over Covid custody killings",
      "link": "https://www.bbc.com/news/articles/ce8l0md9gl1o?at_medium=RSS&at_campaign=rss",
      "summary": "The father and son died in jail after being arrested on suspicion of breaching Covid lockdown rules in 2020.",
      "published": "Mon, 06 Apr 2026 21:21:13 GMT",
      "updated": "Mon, 06 Apr 2026 21:21:13 GMT",
      "id": "https://www.bbc.com/news/articles/ce8l0md9gl1o#0"
    },
    {
      "category": "politics",
      "source_name": "BBC World",
      "feed_url": "http://feeds.bbci.co.uk/news/world/rss.xml",
      "title": "Lil Nas X assault case to be dismissed if he completes mental health programme",
      "link": "https://www.bbc.com/news/articles/cew7nqn5rqgo?at_medium=RSS&at_campaign=rss",
      "summary": "The judge said the musician's behaviour when he was arrested in LA last year was \"aberrant from his normal conduct\".",
      "published": "Mon, 06 Apr 2026 21:55:11 GMT",
      "updated": "Mon, 06 Apr 2026 21:55:11 GMT",
      "id": "https://www.bbc.com/news/articles/cew7nqn5rqgo#0"
    },
    {
      "category": "politics",
      "source_name": "BBC World",
      "feed_url": "http://feeds.bbci.co.uk/news/world/rss.xml",
      "title": "Ten killed in Israeli strikes and clashes between Hamas and militia in Gaza, local sources say",
      "link": "https://www.bbc.com/news/articles/c77md512n71o?at_medium=RSS&at_campaign=rss",
      "summary": "The Israeli strikes reportedly targeted Hamas security personnel after they clashed with an Israeli-backed militia near Maghazi camp.",
      "published": "Mon, 06 Apr 2026 19:11:20 GMT",
      "updated": "Mon, 06 Apr 2026 19:11:20 GMT",
      "id": "https://www.bbc.com/news/articles/c77md512n71o#1"
    },
    {
      "category": "politics",
      "source_name": "BBC World",
      "feed_url": "http://feeds.bbci.co.uk/news/world/rss.xml",
      "title": "Trump endorses ex-UK political aide Steve Hilton for California governor",
      "link": "https://www.bbc.com/news/articles/c0mj4jeyvmzo?at_medium=RSS&at_campaign=rss",
      "summary": "Steve Hilton, who advised the former prime minster and hosted a Fox News show, is running as a Republican.",
      "published": "Mon, 06 Apr 2026 18:55:45 GMT",
      "updated": "Mon, 06 Apr 2026 18:55:45 GMT",
      "id": "https://www.bbc.com/news/articles/c0mj4jeyvmzo#1"
    },
    {
      "category": "politics",
      "source_name": "BBC World",
      "feed_url": "http://feeds.bbci.co.uk/news/world/rss.xml",
      "title": "Seven Eritrean players fail to return home after international match",
      "link": "https://www.bbc.com/news/articles/c747037e2kgo?at_medium=RSS&at_campaign=rss",
      "summary": "Several footballers have absconded in the past leaving behind what rights groups call a repressive government.",
      "published": "Mon, 06 Apr 2026 17:31:33 GMT",
      "updated": "Mon, 06 Apr 2026 17:31:33 GMT",
      "id": "https://www.bbc.com/news/articles/c747037e2kgo#1"
    },
    {
      "category": "politics",
      "source_name": "BBC World",
      "feed_url": "http://feeds.bbci.co.uk/news/world/rss.xml",
      "title": "'Really feeling the love' - Savannah Guthrie returns to NBC as search for mother goes on",
      "link": "https://www.bbc.com/news/articles/c04xqglg7xgo?at_medium=RSS&at_campaign=rss",
      "summary": "Nancy Guthrie disappeared from her home in Tucson, Arizona, in what authorities believe was an abduction.",
      "published": "Mon, 06 Apr 2026 18:07:46 GMT",
      "updated": "Mon, 06 Apr 2026 18:07:46 GMT",
      "id": "https://www.bbc.com/news/articles/c04xqglg7xgo#1"
    },
    {
      "category": "politics",
      "source_name": "BBC World",
      "feed_url": "http://feeds.bbci.co.uk/news/world/rss.xml",
      "title": "Locals dispute Nigerian army claim of 31 rescued after Easter attack",
      "link": "https://www.bbc.com/news/articles/cgld111d9jpo?at_medium=RSS&at_campaign=rss",
      "summary": "Five civilians were killed by the gunmen and their bodies were recovered at the scene, the army said.",
      "published": "Tue, 07 Apr 2026 06:41:24 GMT",
      "updated": "Tue, 07 Apr 2026 06:41:24 GMT",
      "id": "https://www.bbc.com/news/articles/cgld111d9jpo#1"
    },
    {
      "category": "politics",
      "source_name": "BBC World",
      "feed_url": "http://feeds.bbci.co.uk/news/world/rss.xml",
      "title": "US Supreme Court paves way for dismissal of Steve Bannon conviction",
      "link": "https://www.bbc.com/news/articles/cgqk4kyj4yvo?at_medium=RSS&at_campaign=rss",
      "summary": "The order allows a lower court to consider dismissing the former Trump strategist's indictment.",
      "published": "Mon, 06 Apr 2026 16:43:14 GMT",
      "updated": "Mon, 06 Apr 2026 16:43:14 GMT",
      "id": "https://www.bbc.com/news/articles/cgqk4kyj4yvo#1"
    },
    {
      "category": "politics",
      "source_name": "BBC World",
      "feed_url": "http://feeds.bbci.co.uk/news/world/rss.xml",
      "title": "Ladysmith Black Mambazo's 'wise elder' dies aged 77",
      "link": "https://www.bbc.com/news/articles/cx2r5g7x25yo?at_medium=RSS&at_campaign=rss",
      "summary": "Albert Mazibuko sang in the iconic South African choral group for more than 55 years.",
      "published": "Mon, 06 Apr 2026 17:20:16 GMT",
      "updated": "Mon, 06 Apr 2026 17:20:16 GMT",
      "id": "https://www.bbc.com/news/articles/cx2r5g7x25yo#1"
    },
    {
      "category": "politics",
      "source_name": "BBC World",
      "feed_url": "http://feeds.bbci.co.uk/news/world/rss.xml",
      "title": "Emergency jabs after 100 children die of suspected measles in a month in Bangladesh",
      "link": "https://www.bbc.com/news/articles/cevkz2z7dm8o?at_medium=RSS&at_campaign=rss",
      "summary": "More than 100 people, mostly children, have been killed by measles since mid-March, officials suspect.",
      "published": "Mon, 06 Apr 2026 09:59:40 GMT",
      "updated": "Mon, 06 Apr 2026 09:59:40 GMT",
      "id": "https://www.bbc.com/news/articles/cevkz2z7dm8o#1"
    },
    {
      "category": "politics",
      "source_name": "BBC World",
      "feed_url": "http://feeds.bbci.co.uk/news/world/rss.xml",
      "title": "Young gray whale dies after swimming up river in Washington state",
      "link": "https://www.bbc.com/news/articles/cew7n4glz54o?at_medium=RSS&at_campaign=rss",
      "summary": "Hunger is a likely reason the whale, dubbed Willapa Willy, travelled inland, experts say.",
      "published": "Mon, 06 Apr 2026 11:25:32 GMT",
      "updated": "Mon, 06 Apr 2026 11:25:32 GMT",
      "id": "https://www.bbc.com/news/articles/cew7n4glz54o#1"
    },
    {
      "category": "politics",
      "source_name": "BBC World",
      "feed_url": "http://feeds.bbci.co.uk/news/world/rss.xml",
      "title": "China is winning one AI race, the US another - but either might pull ahead",
      "link": "https://www.bbc.com/news/articles/c145enxln0go?at_medium=RSS&at_campaign=rss",
      "summary": "Both sides don't want to let their rival dominate. And the competition may yet be transformed further.",
      "published": "Tue, 07 Apr 2026 05:13:12 GMT",
      "updated": "Tue, 07 Apr 2026 05:13:12 GMT",
      "id": "https://www.bbc.com/news/articles/c145enxln0go#2"
    },
    {
      "category": "politics",
      "source_name": "BBC World",
      "feed_url": "http://feeds.bbci.co.uk/news/world/rss.xml",
      "title": "How rescue of US airman in remote part of Iran unfolded",
      "link": "https://www.bbc.com/news/articles/cx2vpz1kwreo?at_medium=RSS&at_campaign=rss",
      "summary": "The operation to extract him from the ground in hostile territory was hugely complex and involved multiple US government agencies.",
      "published": "Mon, 06 Apr 2026 21:31:24 GMT",
      "updated": "Mon, 06 Apr 2026 21:31:24 GMT",
      "id": "https://www.bbc.com/news/articles/cx2vpz1kwreo#2"
    },
    {
      "category": "politics",
      "source_name": "BBC World",
      "feed_url": "http://feeds.bbci.co.uk/news/world/rss.xml",
      "title": "Fake Australian, Chinese and Brazilian police stations: BBC goes inside a seized scam compound",
      "link": "https://www.bbc.com/news/articles/cjenpy8gx71o?at_medium=RSS&at_campaign=rss",
      "summary": "Almost nothing was known about the Royal Hill casino until the Thai military took control of it in December.",
      "published": "Mon, 06 Apr 2026 23:09:23 GMT",
      "updated": "Mon, 06 Apr 2026 23:09:23 GMT",
      "id": "https://www.bbc.com/news/articles/cjenpy8gx71o#2"
    },
    {
      "category": "politics",
      "source_name": "BBC World",
      "feed_url": "http://feeds.bbci.co.uk/news/world/rss.xml",
      "title": "'We're sinking deeper': Iranians brace for infrastructure strikes as Trump deadline nears",
      "link": "https://www.bbc.com/news/articles/cvgl0ng8z0do?at_medium=RSS&at_campaign=rss",
      "summary": "Ordinary Iranians respond to the US president's threat to destroy Iran's power plants and bridges unless it opens the Strait of Hormuz.",
      "published": "Mon, 06 Apr 2026 15:40:35 GMT",
      "updated": "Mon, 06 Apr 2026 15:40:35 GMT",
      "id": "https://www.bbc.com/news/articles/cvgl0ng8z0do#2"
    },
    {
      "category": "politics",
      "source_name": "BBC World",
      "feed_url": "http://feeds.bbci.co.uk/news/world/rss.xml",
      "title": "Artemis's stunning Moon pictures - science or holiday photos?",
      "link": "https://www.bbc.com/news/articles/clye6j0g840o?at_medium=RSS&at_campaign=rss",
      "summary": "The story behind the beautiful pictures beamed back to Earth from the Artemis II astronauts.",
      "published": "Sun, 05 Apr 2026 15:03:19 GMT",
      "updated": "Sun, 05 Apr 2026 15:03:19 GMT",
      "id": "https://www.bbc.com/news/articles/clye6j0g840o#2"
    },
    {
      "category": "politics",
      "source_name": "BBC World",
      "feed_url": "http://feeds.bbci.co.uk/news/world/rss.xml",
      "title": "'I adore her now': Mother learns to cope with child's autism in a country with little help",
      "link": "https://www.bbc.com/news/articles/cj608n98z1jo?at_medium=RSS&at_campaign=rss",
      "summary": "Malawian Martha Ongwane, brought low by her daughter's autism, found a rare support group.",
      "published": "Sun, 05 Apr 2026 23:32:20 GMT",
      "updated": "Sun, 05 Apr 2026 23:32:20 GMT",
      "id": "https://www.bbc.com/news/articles/cj608n98z1jo#2"
    },
    {
      "category": "politics",
      "source_name": "BBC World",
      "feed_url": "http://feeds.bbci.co.uk/news/world/rss.xml",
      "title": "'We are at the edge of a battlefield': BBC reports near Strait of Hormuz",
      "link": "https://www.bbc.com/news/videos/c3r3vw4j38do?at_medium=RSS&at_campaign=rss",
      "summary": "The BBC's Orla Guerin travels to the edge of the critical waterway that Iran has put a stranglehold on.",
      "published": "Sun, 05 Apr 2026 21:30:19 GMT",
      "updated": "Sun, 05 Apr 2026 21:30:19 GMT",
      "id": "https://www.bbc.com/news/videos/c3r3vw4j38do#3"
    },
    {
      "category": "politics",
      "source_name": "BBC World",
      "feed_url": "http://feeds.bbci.co.uk/news/world/rss.xml",
      "title": "'Absolutely spectacular': Artemis II crew see first glimpse of far side of Moon",
      "link": "https://www.bbc.com/news/videos/ce3d5gkd2geo?at_medium=RSS&at_campaign=rss",
      "summary": "Astronauts on the Artemis II mission are on the third day of their journey around the far side of the Moon.",
      "published": "Sun, 05 Apr 2026 00:04:03 GMT",
      "updated": "Sun, 05 Apr 2026 00:04:03 GMT",
      "id": "https://www.bbc.com/news/videos/ce3d5gkd2geo#3"
    },
    {
      "category": "politics",
      "source_name": "BBC World",
      "feed_url": "http://feeds.bbci.co.uk/news/world/rss.xml",
      "title": "What we know so far about the search for missing US airman in Iran",
      "link": "https://www.bbc.com/news/videos/c7vqlr5gqr0o?at_medium=RSS&at_campaign=rss",
      "summary": "US and Iranian forces are searching for a missing American crew member after a US warplane was shot down.",
      "published": "Sat, 04 Apr 2026 11:00:34 GMT",
      "updated": "Sat, 04 Apr 2026 11:00:34 GMT",
      "id": "https://www.bbc.com/news/videos/c7vqlr5gqr0o#3"
    },
    {
      "category": "politics",
      "source_name": "BBC World",
      "feed_url": "http://feeds.bbci.co.uk/news/world/rss.xml",
      "title": "Watch: Artemis II's journey so far as it leaves Earth orbit... in 85 seconds",
      "link": "https://www.bbc.com/news/videos/cpqxn8zx8ydo?at_medium=RSS&at_campaign=rss",
      "summary": "The crew will not land on the Moon on this current mission, though Nasa is preparing for a potential lunar landing by 2028.",
      "published": "Fri, 03 Apr 2026 13:06:18 GMT",
      "updated": "Fri, 03 Apr 2026 13:06:18 GMT",
      "id": "https://www.bbc.com/news/videos/cpqxn8zx8ydo#3"
    }
  ]
}